viash/__version__.py
viash-0.1.dev0.dist-info/METADATA
viash-0.1.dev0.dist-info/WHEEL
viash-0.1.dev0.dist-info/top_level.txt
viash-0.1.dev0.dist-info/RECORD
